pulldocker/__init__.py
pulldocker/command_line_options.py
pulldocker/constants.py
pulldocker/main.py
pulldocker/profile.py
pulldocker/pulldocker.py
pulldocker/repository.py
pulldocker/tag.py
pulldocker/yaml_parser.py
pulldocker-0.4.4.dist-info/licenses/LICENSE
pulldocker-0.4.4.dist-info/METADATA
pulldocker-0.4.4.dist-info/WHEEL
pulldocker-0.4.4.dist-info/entry_points.txt
pulldocker-0.4.4.dist-info/top_level.txt
pulldocker-0.4.4.dist-info/RECORD
