Metadata-Version: 2.4
Name: PullDocker
Version: 0.4.4
Summary: Watch git repositories for Docker compose configuration changes
Author-email: Fabio Castelli <muflone@muflone.com>
License-Expression: GPL-3.0-or-later
Project-URL: Homepage, http://www.muflone.com/pulldocker/
Project-URL: Source, https://github.com/muflone/pulldocker/
Project-URL: Issues, https://github.com/muflone/pulldocker/issues
Project-URL: Releases, https://github.com/muflone/pulldocker/releases
Classifier: Development Status :: 1 - Planning
Classifier: Intended Audience :: Developers
Classifier: Operating System :: OS Independent
Classifier: Programming Language :: Python :: 3
Classifier: Programming Language :: Python :: 3.10
Classifier: Programming Language :: Python :: 3.11
Classifier: Programming Language :: Python :: 3.12
Classifier: Programming Language :: Python :: 3.13
License-File: LICENSE
Requires-Dist: pyyaml~=6.0
Requires-Dist: gitpython~=3.1
Dynamic: license-file
